scMAGCA/Dataset.py
scMAGCA/__init__.py
scMAGCA/layers.py
scMAGCA/loss.py
scMAGCA/preprocess.py
scMAGCA/run_scMAGCA.py
scMAGCA/run_scMAGCA_3omics.py
scMAGCA/run_scMAGCA_batch.py
scMAGCA/scMAGCA.py
scMAGCA/scMAGCA_3omics.py
scMAGCA/scMAGCA_batch.py
scMAGCA/utils.py
scMAGCA-1.0.9.dist-info/LICENSE
scMAGCA-1.0.9.dist-info/METADATA
scMAGCA-1.0.9.dist-info/WHEEL
scMAGCA-1.0.9.dist-info/top_level.txt
scMAGCA-1.0.9.dist-info/RECORD
