Metadata-Version: 2.1
Name: scMAGCA
Version: 1.0.9
Summary: scMAGCA, a multi-omics adversarial graph convolutional autoencoder framework to extract interpretable latent embeddings that characterize scMultiomics data.
Home-page: https://github.com/zemingzhou30/scMAGCA
Author: zhouzeming
Author-email: 657608841@qq.com
Classifier: Programming Language :: Python :: 3
Classifier: License :: OSI Approved :: MIT License
Classifier: Operating System :: OS Independent
License-File: LICENSE
